llama_index/postprocessor/flashrank_rerank/__init__.py
llama_index/postprocessor/flashrank_rerank/base.py
llama_index_postprocessor_flashrank_rerank-0.2.1.dist-info/METADATA
llama_index_postprocessor_flashrank_rerank-0.2.1.dist-info/WHEEL
llama_index_postprocessor_flashrank_rerank-0.2.1.dist-info/licenses/LICENSE
llama_index_postprocessor_flashrank_rerank-0.2.1.dist-info/RECORD
