Metadata-Version: 2.4
Name: llama-index-postprocessor-flashrank-rerank
Version: 0.2.1
Summary: llama-index postprocessor FlashRank rerank integration
Author-email: Bill Easton <williamseaston@gmail.com>
License-Expression: MIT
License-File: LICENSE
Requires-Python: <4.0,>=3.10
Requires-Dist: flashrank>=0.2.10
Requires-Dist: llama-index-core<0.15,>=0.13.0
